bidgely/__init__.py
bidgely/bidgely.py
bidgely/exceptions.py
bidgely/tests/__init__.py
bidgely/utilities/__init__.py
bidgely/utilities/aws_srp.py
bidgely/utilities/base.py
bidgely/utilities/bchydro.py
bidgely/utilities/hydroone.py
bidgely/utilities/hydroottawa.py
bidgely/utilities/nspower.py
bidgely-0.1.5.dist-info/LICENSE
bidgely-0.1.5.dist-info/METADATA
bidgely-0.1.5.dist-info/WHEEL
bidgely-0.1.5.dist-info/RECORD
