Metadata-Version: 2.1
Name: bidgely
Version: 0.1.5
Summary: A python library for downloading your historical data fromutilities that use Bidgely
License: Apache-2.0
Author: Carter Green
Author-email: carter.green@icloud.com
Requires-Python: >=3.10,<4.0
Classifier: License :: OSI Approved :: Apache Software License
Classifier: Programming Language :: Python :: 3
Classifier: Programming Language :: Python :: 3.10
Classifier: Programming Language :: Python :: 3.11
Requires-Dist: aiohttp (>=3.8.5,<4.0.0)
Requires-Dist: boto3 (>=1.26.32,<2.0.0)
Requires-Dist: pre-commit (>=3.0.0)
Requires-Dist: py3rijndael (>=0.3.3,<0.4.0)
